cjieba/__init__.py
cjieba/_native.py
cjieba/_native__ffi.py
cjieba/_native__lib.so
cjieba/dict/hmm_model.utf8
cjieba/dict/idf.utf8
cjieba/dict/jieba.dict.utf8
cjieba/dict/stop_words.utf8
cjieba/dict/user.dict.utf8
cjieba-0.4.4.dist-info/LICENSE
cjieba-0.4.4.dist-info/METADATA
cjieba-0.4.4.dist-info/WHEEL
cjieba-0.4.4.dist-info/top_level.txt
cjieba-0.4.4.dist-info/RECORD
