Metadata-Version: 2.1
Name: cjieba
Version: 0.4.4
Summary: Python cffi binding for cjieba
Home-page: https://github.com/messense/cjieba-py
Author: messense
Author-email: messense@icloud.com
License: UNKNOWN
Platform: any
Requires-Dist: milksnake
